snipprcomparison
