Metadata-Version: 1.1
Name: snipprcomparison
Version: 0.0.5
Summary: A package used to compare two snippets of code.
Home-page: https://github.com/Zeshiba/snipprcomparison
Author: Joshua Isanan
Author-email: joshuaisanan@gmail.com
License: UNKNOWN
Platform: UNKNOWN
Classifier: Programming Language :: Python :: 3
Classifier: Operating System :: OS Independent
